markdown_helper/__init__.py
markdown_helper-1.0.2.dist-info/METADATA
markdown_helper-1.0.2.dist-info/WHEEL
markdown_helper-1.0.2.dist-info/licenses/LICENSE
markdown_helper-1.0.2.dist-info/RECORD
